Compiled from "D:\IdeaProjects\TlDemo\src\demo\MathDemo.tl"
public class demo.MathDemo {
  public demo.MathDemo();
    Code:
       0: aload_0
       1: invokespecial #12                 // Method java/lang/Object."<init>":()V
       4: return

  static org.toylang.core.wrappers.TObject f(org.toylang.core.wrappers.TObject);
    Code:
       0: aload_0
       1: getstatic     #16                 // Field __CONSTANTS__:[Lorg/toylang/core/wrappers/TObject;
       4: ldc           #17                 // int 0
       6: aaload
       7: invokevirtual #22                 // Method org/toylang/core/wrappers/TObject.pow:(Lorg/toylang/core/wrappers/TObject;)Lorg/toylang/core/wrappers/TObject;
      10: aload_0
      11: invokevirtual #25                 // Method org/toylang/core/wrappers/TObject.add:(Lorg/toylang/core/wrappers/TObject;)Lorg/toylang/core/wrappers/TObject;
      14: getstatic     #16                 // Field __CONSTANTS__:[Lorg/toylang/core/wrappers/TObject;
      17: ldc           #26                 // int 1
      19: aaload
      20: invokevirtual #25                 // Method org/toylang/core/wrappers/TObject.add:(Lorg/toylang/core/wrappers/TObject;)Lorg/toylang/core/wrappers/TObject;
      23: areturn

  static org.toylang.core.wrappers.TObject g(org.toylang.core.wrappers.TObject);
    Code:
       0: getstatic     #16                 // Field __CONSTANTS__:[Lorg/toylang/core/wrappers/TObject;
       3: ldc           #28                 // int 2
       5: aaload
       6: aload_0
       7: invokevirtual #31                 // Method org/toylang/core/wrappers/TObject.mul:(Lorg/toylang/core/wrappers/TObject;)Lorg/toylang/core/wrappers/TObject;
      10: getstatic     #16                 // Field __CONSTANTS__:[Lorg/toylang/core/wrappers/TObject;
      13: ldc           #32                 // int 3
      15: aaload
      16: invokevirtual #25                 // Method org/toylang/core/wrappers/TObject.add:(Lorg/toylang/core/wrappers/TObject;)Lorg/toylang/core/wrappers/TObject;
      19: areturn

  static org.toylang.core.wrappers.TObject fog(org.toylang.core.wrappers.TObject);
    Code:
       0: aload_0
       1: invokestatic  #35                 // Method g:(Lorg/toylang/core/wrappers/TObject;)Lorg/toylang/core/wrappers/TObject;
       4: invokestatic  #37                 // Method f:(Lorg/toylang/core/wrappers/TObject;)Lorg/toylang/core/wrappers/TObject;
       7: areturn

  public static org.toylang.core.wrappers.TObject factorial(org.toylang.core.wrappers.TObject);
    Code:
       0: aload_0
       1: getstatic     #16                 // Field __CONSTANTS__:[Lorg/toylang/core/wrappers/TObject;
       4: ldc           #26                 // int 1
       6: aaload
       7: invokevirtual #41                 // Method org/toylang/core/wrappers/TObject.LTE:(Lorg/toylang/core/wrappers/TObject;)Lorg/toylang/core/wrappers/TObject;
      10: invokevirtual #45                 // Method org/toylang/core/wrappers/TObject.isTrue:()Z
      13: ifeq          18
      16: aload_0
      17: areturn
      18: aload_0
      19: aload_0
      20: getstatic     #16                 // Field __CONSTANTS__:[Lorg/toylang/core/wrappers/TObject;
      23: ldc           #26                 // int 1
      25: aaload
      26: invokevirtual #48                 // Method org/toylang/core/wrappers/TObject.sub:(Lorg/toylang/core/wrappers/TObject;)Lorg/toylang/core/wrappers/TObject;
      29: invokestatic  #50                 // Method factorial:(Lorg/toylang/core/wrappers/TObject;)Lorg/toylang/core/wrappers/TObject;
      32: invokevirtual #31                 // Method org/toylang/core/wrappers/TObject.mul:(Lorg/toylang/core/wrappers/TObject;)Lorg/toylang/core/wrappers/TObject;
      35: areturn

  public static org.toylang.core.wrappers.TObject fib(org.toylang.core.wrappers.TObject);
    Code:
       0: aload_0
       1: getstatic     #16                 // Field __CONSTANTS__:[Lorg/toylang/core/wrappers/TObject;
       4: ldc           #52                 // int 4
       6: aaload
       7: invokevirtual #55                 // Method org/toylang/core/wrappers/TObject.EQ:(Lorg/toylang/core/wrappers/TObject;)Lorg/toylang/core/wrappers/TObject;
      10: invokevirtual #45                 // Method org/toylang/core/wrappers/TObject.isTrue:()Z
      13: ifeq          23
      16: getstatic     #16                 // Field __CONSTANTS__:[Lorg/toylang/core/wrappers/TObject;
      19: ldc           #52                 // int 4
      21: aaload
      22: areturn
      23: aload_0
      24: getstatic     #16                 // Field __CONSTANTS__:[Lorg/toylang/core/wrappers/TObject;
      27: ldc           #26                 // int 1
      29: aaload
      30: invokevirtual #55                 // Method org/toylang/core/wrappers/TObject.EQ:(Lorg/toylang/core/wrappers/TObject;)Lorg/toylang/core/wrappers/TObject;
      33: invokevirtual #45                 // Method org/toylang/core/wrappers/TObject.isTrue:()Z
      36: ifeq          46
      39: getstatic     #16                 // Field __CONSTANTS__:[Lorg/toylang/core/wrappers/TObject;
      42: ldc           #26                 // int 1
      44: aaload
      45: areturn
      46: aload_0
      47: getstatic     #16                 // Field __CONSTANTS__:[Lorg/toylang/core/wrappers/TObject;
      50: ldc           #26                 // int 1
      52: aaload
      53: invokevirtual #48                 // Method org/toylang/core/wrappers/TObject.sub:(Lorg/toylang/core/wrappers/TObject;)Lorg/toylang/core/wrappers/TObject;
      56: invokestatic  #57                 // Method fib:(Lorg/toylang/core/wrappers/TObject;)Lorg/toylang/core/wrappers/TObject;
      59: aload_0
      60: getstatic     #16                 // Field __CONSTANTS__:[Lorg/toylang/core/wrappers/TObject;
      63: ldc           #17                 // int 0
      65: aaload
      66: invokevirtual #48                 // Method org/toylang/core/wrappers/TObject.sub:(Lorg/toylang/core/wrappers/TObject;)Lorg/toylang/core/wrappers/TObject;
      69: invokestatic  #57                 // Method fib:(Lorg/toylang/core/wrappers/TObject;)Lorg/toylang/core/wrappers/TObject;
      72: invokevirtual #25                 // Method org/toylang/core/wrappers/TObject.add:(Lorg/toylang/core/wrappers/TObject;)Lorg/toylang/core/wrappers/TObject;
      75: areturn

  public static void main(java.lang.String[]);
    Code:
       0: getstatic     #16                 // Field __CONSTANTS__:[Lorg/toylang/core/wrappers/TObject;
       3: ldc           #60                 // int 5
       5: aaload
       6: invokestatic  #65                 // Method toylang/Builtin.println:(Lorg/toylang/core/wrappers/TObject;)Lorg/toylang/core/wrappers/TObject;
       9: pop
      10: invokestatic  #69                 // Method toylang/Builtin.readLine:()Lorg/toylang/core/wrappers/TObject;
      13: invokestatic  #72                 // Method toylang/Builtin.int:(Lorg/toylang/core/wrappers/TObject;)Lorg/toylang/core/wrappers/TObject;
      16: astore_1
      17: getstatic     #16                 // Field __CONSTANTS__:[Lorg/toylang/core/wrappers/TObject;
      20: ldc           #73                 // int 6
      22: aaload
      23: aload_1
      24: invokevirtual #25                 // Method org/toylang/core/wrappers/TObject.add:(Lorg/toylang/core/wrappers/TObject;)Lorg/toylang/core/wrappers/TObject;
      27: getstatic     #16                 // Field __CONSTANTS__:[Lorg/toylang/core/wrappers/TObject;
      30: ldc           #74                 // int 7
      32: aaload
      33: invokevirtual #25                 // Method org/toylang/core/wrappers/TObject.add:(Lorg/toylang/core/wrappers/TObject;)Lorg/toylang/core/wrappers/TObject;
      36: aload_1
      37: invokestatic  #37                 // Method f:(Lorg/toylang/core/wrappers/TObject;)Lorg/toylang/core/wrappers/TObject;
      40: invokevirtual #25                 // Method org/toylang/core/wrappers/TObject.add:(Lorg/toylang/core/wrappers/TObject;)Lorg/toylang/core/wrappers/TObject;
      43: getstatic     #16                 // Field __CONSTANTS__:[Lorg/toylang/core/wrappers/TObject;
      46: ldc           #75                 // int 8
      48: aaload
      49: invokevirtual #25                 // Method org/toylang/core/wrappers/TObject.add:(Lorg/toylang/core/wrappers/TObject;)Lorg/toylang/core/wrappers/TObject;
      52: aload_1
      53: invokestatic  #35                 // Method g:(Lorg/toylang/core/wrappers/TObject;)Lorg/toylang/core/wrappers/TObject;
      56: invokevirtual #25                 // Method org/toylang/core/wrappers/TObject.add:(Lorg/toylang/core/wrappers/TObject;)Lorg/toylang/core/wrappers/TObject;
      59: getstatic     #16                 // Field __CONSTANTS__:[Lorg/toylang/core/wrappers/TObject;
      62: ldc           #76                 // int 9
      64: aaload
      65: invokevirtual #25                 // Method org/toylang/core/wrappers/TObject.add:(Lorg/toylang/core/wrappers/TObject;)Lorg/toylang/core/wrappers/TObject;
      68: aload_1
      69: invokestatic  #78                 // Method fog:(Lorg/toylang/core/wrappers/TObject;)Lorg/toylang/core/wrappers/TObject;
      72: invokevirtual #25                 // Method org/toylang/core/wrappers/TObject.add:(Lorg/toylang/core/wrappers/TObject;)Lorg/toylang/core/wrappers/TObject;
      75: invokestatic  #65                 // Method toylang/Builtin.println:(Lorg/toylang/core/wrappers/TObject;)Lorg/toylang/core/wrappers/TObject;
      78: pop
      79: getstatic     #16                 // Field __CONSTANTS__:[Lorg/toylang/core/wrappers/TObject;
      82: ldc           #79                 // int 10
      84: aaload
      85: aload_1
      86: invokestatic  #50                 // Method factorial:(Lorg/toylang/core/wrappers/TObject;)Lorg/toylang/core/wrappers/TObject;
      89: invokevirtual #25                 // Method org/toylang/core/wrappers/TObject.add:(Lorg/toylang/core/wrappers/TObject;)Lorg/toylang/core/wrappers/TObject;
      92: getstatic     #16                 // Field __CONSTANTS__:[Lorg/toylang/core/wrappers/TObject;
      95: ldc           #80                 // int 11
      97: aaload
      98: invokevirtual #25                 // Method org/toylang/core/wrappers/TObject.add:(Lorg/toylang/core/wrappers/TObject;)Lorg/toylang/core/wrappers/TObject;
     101: aload_1
     102: invokestatic  #57                 // Method fib:(Lorg/toylang/core/wrappers/TObject;)Lorg/toylang/core/wrappers/TObject;
     105: invokevirtual #25                 // Method org/toylang/core/wrappers/TObject.add:(Lorg/toylang/core/wrappers/TObject;)Lorg/toylang/core/wrappers/TObject;
     108: invokestatic  #65                 // Method toylang/Builtin.println:(Lorg/toylang/core/wrappers/TObject;)Lorg/toylang/core/wrappers/TObject;
     111: pop
     112: return

  static {};
    Code:
       0: ldc           #82                 // int 12
       2: anewarray     #19                 // class org/toylang/core/wrappers/TObject
       5: dup
       6: ldc           #17                 // int 0
       8: new           #84                 // class org/toylang/core/wrappers/TInt
      11: dup
      12: ldc           #28                 // int 2
      14: invokespecial #87                 // Method org/toylang/core/wrappers/TInt."<init>":(I)V
      17: aastore
      18: dup
      19: ldc           #26                 // int 1
      21: new           #84                 // class org/toylang/core/wrappers/TInt
      24: dup
      25: ldc           #26                 // int 1
      27: invokespecial #87                 // Method org/toylang/core/wrappers/TInt."<init>":(I)V
      30: aastore
      31: dup
      32: ldc           #28                 // int 2
      34: new           #84                 // class org/toylang/core/wrappers/TInt
      37: dup
      38: ldc           #52                 // int 4
      40: invokespecial #87                 // Method org/toylang/core/wrappers/TInt."<init>":(I)V
      43: aastore
      44: dup
      45: ldc           #32                 // int 3
      47: new           #84                 // class org/toylang/core/wrappers/TInt
      50: dup
      51: ldc           #88                 // int 50
      53: invokespecial #87                 // Method org/toylang/core/wrappers/TInt."<init>":(I)V
      56: aastore
      57: dup
      58: ldc           #52                 // int 4
      60: new           #84                 // class org/toylang/core/wrappers/TInt
      63: dup
      64: ldc           #17                 // int 0
      66: invokespecial #87                 // Method org/toylang/core/wrappers/TInt."<init>":(I)V
      69: aastore
      70: dup
      71: ldc           #60                 // int 5
      73: new           #90                 // class org/toylang/core/wrappers/TString
      76: dup
      77: ldc           #92                 // String Enter a number:
      79: invokespecial #95                 // Method org/toylang/core/wrappers/TString."<init>":(Ljava/lang/String;)V
      82: aastore
      83: dup
      84: ldc           #73                 // int 6
      86: new           #90                 // class org/toylang/core/wrappers/TString
      89: dup
      90: ldc           #97                 // String x =
      92: invokespecial #95                 // Method org/toylang/core/wrappers/TString."<init>":(Ljava/lang/String;)V
      95: aastore
      96: dup
      97: ldc           #74                 // int 7
      99: new           #90                 // class org/toylang/core/wrappers/TString
     102: dup
     103: ldc           #99                 // String , f(x) =
     105: invokespecial #95                 // Method org/toylang/core/wrappers/TString."<init>":(Ljava/lang/String;)V
     108: aastore
     109: dup
     110: ldc           #75                 // int 8
     112: new           #90                 // class org/toylang/core/wrappers/TString
     115: dup
     116: ldc           #101                // String , g(x) =
     118: invokespecial #95                 // Method org/toylang/core/wrappers/TString."<init>":(Ljava/lang/String;)V
     121: aastore
     122: dup
     123: ldc           #76                 // int 9
     125: new           #90                 // class org/toylang/core/wrappers/TString
     128: dup
     129: ldc           #103                // String , fog(x) =
     131: invokespecial #95                 // Method org/toylang/core/wrappers/TString."<init>":(Ljava/lang/String;)V
     134: aastore
     135: dup
     136: ldc           #79                 // int 10
     138: new           #90                 // class org/toylang/core/wrappers/TString
     141: dup
     142: ldc           #105                // String x! =
     144: invokespecial #95                 // Method org/toylang/core/wrappers/TString."<init>":(Ljava/lang/String;)V
     147: aastore
     148: dup
     149: ldc           #80                 // int 11
     151: new           #90                 // class org/toylang/core/wrappers/TString
     154: dup
     155: ldc           #107                // String , fib(x) =
     157: invokespecial #95                 // Method org/toylang/core/wrappers/TString."<init>":(Ljava/lang/String;)V
     160: aastore
     161: putstatic     #16                 // Field __CONSTANTS__:[Lorg/toylang/core/wrappers/TObject;
     164: return
}
